setup.py
alabi_probability/Binomialdistribution.py
alabi_probability/Gaussiandistribution.py
alabi_probability/Generaldistribution.py
alabi_probability/__init__.py
alabi_probability.egg-info/PKG-INFO
alabi_probability.egg-info/SOURCES.txt
alabi_probability.egg-info/dependency_links.txt
alabi_probability.egg-info/not-zip-safe
alabi_probability.egg-info/top_level.txt