Metadata-Version: 1.0
Name: alabi-probability
Version: 1.0
Summary: Gaussian and Binomial distributions
Home-page: UNKNOWN
Author: Alabi A.
Author-email: UNKNOWN
License: UNKNOWN
Platform: UNKNOWN
